onnx_diff/__init__.py
onnx_diff/diff.py
onnx_diff/run.py
onnx_diff/structs.py
onnx_diff/utils.py
onnx_diff-0.1.2.dist-info/entry_points.txt
onnx_diff-0.1.2.dist-info/WHEEL
onnx_diff-0.1.2.dist-info/METADATA
onnx_diff-0.1.2.dist-info/RECORD
